colossus_sdk/__init__.py
colossus_sdk/colossus_client.py
colossus_sdk/colossus_exceptions.py
colossus_sdk/config.yaml
colossus_sdk/endpoint_server.py
colossus_sdk/mongo_client.py
colossus_sdk/test_rocco.py
colossus_sdk/test_rocco_broadcast.py
colossus_sdk/tester.py
colossus_sdk-0.1.4.dist-info/LICENSE.txt
colossus_sdk-0.1.4.dist-info/METADATA
colossus_sdk-0.1.4.dist-info/WHEEL
colossus_sdk-0.1.4.dist-info/RECORD
