Metadata-Version: 2.1
Name: colossus_sdk
Version: 0.1.4
Summary: A Python SDK for interacting with the Colossus API
Author: Raj Panesar
Author-email: raj@icolossus.digital
Requires-Python: >=3.10,<4.0
Classifier: Programming Language :: Python :: 3
Classifier: Programming Language :: Python :: 3.10
Classifier: Programming Language :: Python :: 3.11
Requires-Dist: flask (>=3.0.0,<4.0.0)
Requires-Dist: pymongo (>=4.6.1,<5.0.0)
Requires-Dist: pyyaml (>=6.0.1,<7.0.0)
Requires-Dist: requests (>=2.31.0,<3.0.0)
